thefuck/__init__.py
thefuck/ai.py
thefuck/argument_parser.py
thefuck/conf.py
thefuck/const.py
thefuck/corrector.py
thefuck/exceptions.py
thefuck/logs.py
thefuck/types.py
thefuck/ui.py
thefuck/utils.py
thefuck/entrypoints/__init__.py
thefuck/entrypoints/alias.py
thefuck/entrypoints/fix_command.py
thefuck/entrypoints/main.py
thefuck/entrypoints/not_configured.py
thefuck/entrypoints/setup.py
thefuck/entrypoints/shell_logger.py
thefuck/output_readers/__init__.py
thefuck/output_readers/read_log.py
thefuck/output_readers/rerun.py
thefuck/output_readers/shell_logger.py
thefuck/rules/__init__.py
thefuck/rules/adb_unknown_command.py
thefuck/rules/ag_literal.py
thefuck/rules/apt_get.py
thefuck/rules/apt_get_search.py
thefuck/rules/apt_invalid_operation.py
thefuck/rules/apt_list_upgradable.py
thefuck/rules/apt_upgrade.py
thefuck/rules/aws_cli.py
thefuck/rules/az_cli.py
thefuck/rules/brew_cask_dependency.py
thefuck/rules/brew_install.py
thefuck/rules/brew_link.py
thefuck/rules/brew_reinstall.py
thefuck/rules/brew_uninstall.py
thefuck/rules/brew_unknown_command.py
thefuck/rules/brew_update_formula.py
thefuck/rules/cargo.py
thefuck/rules/cargo_no_command.py
thefuck/rules/cat_dir.py
thefuck/rules/cd_correction.py
thefuck/rules/cd_cs.py
thefuck/rules/cd_mkdir.py
thefuck/rules/cd_parent.py
thefuck/rules/chmod_x.py
thefuck/rules/choco_install.py
thefuck/rules/composer_not_command.py
thefuck/rules/conda_mistype.py
thefuck/rules/cp_create_destination.py
thefuck/rules/cp_omitting_directory.py
thefuck/rules/cpp11.py
thefuck/rules/dirty_untar.py
thefuck/rules/dirty_unzip.py
thefuck/rules/django_south_ghost.py
thefuck/rules/django_south_merge.py
thefuck/rules/dnf_no_such_command.py
thefuck/rules/docker_image_being_used_by_container.py
thefuck/rules/docker_login.py
thefuck/rules/docker_not_command.py
thefuck/rules/dry.py
thefuck/rules/fab_command_not_found.py
thefuck/rules/fix_alt_space.py
thefuck/rules/fix_file.py
thefuck/rules/gem_unknown_command.py
thefuck/rules/git_add.py
thefuck_leeguoo-3.44.dist-info/licenses/LICENSE.md
thefuck_leeguoo-3.44.dist-info/METADATA
thefuck_leeguoo-3.44.dist-info/WHEEL
thefuck_leeguoo-3.44.dist-info/entry_points.txt
thefuck_leeguoo-3.44.dist-info/top_level.txt
thefuck_leeguoo-3.44.dist-info/RECORD
