Metadata-Version: 2.4
Name: thefuck-leeguoo
Version: 3.44
Summary: AI-first command fixer for shell/terminal CLI with streamed explanations and Markdown rendering
Home-page: https://github.com/leeguooooo/thefuck
Author: leeguoo
Author-email: leeguoo@users.noreply.github.com
License: MIT
Project-URL: Homepage, https://github.com/leeguooooo/thefuck
Project-URL: Repository, https://github.com/leeguooooo/thefuck
Project-URL: Issues, https://github.com/leeguooooo/thefuck/issues
Project-URL: Documentation, https://github.com/leeguooooo/thefuck#readme
Keywords: ai,autocorrect,bash,cli,command line,fish,productivity,shell,terminal,zsh
Requires-Python: >=2.7, !=3.0.*, !=3.1.*, !=3.2.*, !=3.3.*, !=3.4.*
License-File: LICENSE.md
Requires-Dist: psutil
Requires-Dist: colorama
Requires-Dist: six
Requires-Dist: rich; python_version >= "3.8"
Requires-Dist: pathlib2; python_version < "3.4"
Requires-Dist: backports.shutil_get_terminal_size; python_version < "3.3"
Requires-Dist: decorator<5; python_version <= "2.7"
Requires-Dist: pyte<0.8.1; python_version <= "2.7"
Requires-Dist: decorator; python_version > "2.7"
Requires-Dist: pyte; python_version > "2.7"
Requires-Dist: win_unicode_console; sys_platform == "win32"
Provides-Extra: dev
Requires-Dist: flake8>=6; python_version >= "3.8.1" and extra == "dev"
Requires-Dist: pytest<9; python_version >= "3.8" and extra == "dev"
Requires-Dist: mock; python_version >= "3.8" and extra == "dev"
Requires-Dist: pytest-mock; python_version >= "3.8" and extra == "dev"
Requires-Dist: wheel; python_version >= "3.8" and extra == "dev"
Requires-Dist: setuptools>=17.1; python_version >= "3.8" and extra == "dev"
Requires-Dist: pexpect; python_version >= "3.8" and extra == "dev"
Requires-Dist: pypandoc; python_version >= "3.8" and extra == "dev"
Requires-Dist: pytest-benchmark; python_version >= "3.8" and extra == "dev"
Requires-Dist: pytest-docker-pexpect; python_version >= "3.8" and extra == "dev"
Requires-Dist: twine; python_version >= "3.8" and extra == "dev"
Dynamic: author-email
Dynamic: home-page
Dynamic: license-file
Dynamic: requires-python
